geeservermap/__init__.py
geeservermap/async_jobs.py
geeservermap/calls.py
geeservermap/exceptions.py
geeservermap/helpers.py
geeservermap/main.py
geeservermap/map.py
geeservermap/py.typed
geeservermap/elements/__init__.py
geeservermap/elements/layers.py
geeservermap/templates/layout.html
geeservermap/templates/map.html
geeservermap-0.0.0rc2.dist-info/METADATA
geeservermap-0.0.0rc2.dist-info/WHEEL
geeservermap-0.0.0rc2.dist-info/entry_points.txt
geeservermap-0.0.0rc2.dist-info/licenses/AUTHORS.rst
geeservermap-0.0.0rc2.dist-info/licenses/LICENSE
geeservermap-0.0.0rc2.dist-info/RECORD
