Metadata-Version: 2.1
Name: geeservermap
Version: 0.0.0rc2
Summary: Interactive map for Google Earth Engine in python
Project-URL: Homepage, https://github.com/Louis-Dreyfus-Comany/geeservermap
Author-email: LDC Research Repository <remote-sensing@ldc.com>
License: MIT
License-File: AUTHORS.rst
License-File: LICENSE
Keywords: flask,gis,google earth engine,image processing,raster
Classifier: Development Status :: 3 - Alpha
Classifier: Intended Audience :: Developers
Classifier: License :: OSI Approved :: MIT License
Classifier: Programming Language :: Python :: 3.8
Classifier: Programming Language :: Python :: 3.9
Classifier: Programming Language :: Python :: 3.10
Classifier: Programming Language :: Python :: 3.11
Requires-Python: >=3.8
Requires-Dist: brotli
Requires-Dist: deprecated>=1.2.14
Requires-Dist: earthengine-api
Requires-Dist: flask
Requires-Dist: requests
Provides-Extra: doc
Requires-Dist: pydata-sphinx-theme; extra == 'doc'
Requires-Dist: sphinx-autoapi; extra == 'doc'
Requires-Dist: sphinx-copybutton; extra == 'doc'
Requires-Dist: sphinx-design; extra == 'doc'
Requires-Dist: sphinx>=6.2.1; extra == 'doc'
Provides-Extra: test
Requires-Dist: pytest; extra == 'test'
Requires-Dist: pytest-cov; extra == 'test'
Requires-Dist: pytest-deadfixtures; extra == 'test'
Requires-Dist: pytest-sugar; extra == 'test'
